README.md
setup.py
pi_hcsr501/__init__.py
pi_hcsr501/hcsr501.py
pi_hcsr501.egg-info/PKG-INFO
pi_hcsr501.egg-info/SOURCES.txt
pi_hcsr501.egg-info/dependency_links.txt
pi_hcsr501.egg-info/top_level.txt