Metadata-Version: 2.1
Name: pi-hcsr501
Version: 0.5.1
Summary: Library to read hcsr501 sensor.
Home-page: https://github.com/kangasta/pi_hcsr501
Author: Toni Kangas
License: UNKNOWN
Platform: UNKNOWN
Classifier: Programming Language :: Python :: 3
Classifier: License :: OSI Approved :: MIT License
Classifier: Operating System :: OS Independent
